README.rst
setup.py
SQLORMX.egg-info/PKG-INFO
SQLORMX.egg-info/SOURCES.txt
SQLORMX.egg-info/dependency_links.txt
SQLORMX.egg-info/not-zip-safe
SQLORMX.egg-info/requires.txt
SQLORMX.egg-info/top_level.txt
sqlormx/__init__.py
sqlormx/constant.py
sqlormx/log_support.py
sqlormx/orm.py
sqlormx/orm_support.py
sqlormx/snowflake.py
sqlormx/support.py