Metadata-Version: 2.1
Name: SQLORMX
Version: 0.6.0
Summary: A easy，single table ORM framework for python. Support MySQL, PostgreSQL, SQLite etc.
Home-page: https://gitee.com/summry/sqlormx
Author: summy
Author-email: xiazhongbiao@126.com
License: UNKNOWN
Keywords: SQL,MySQL,PostgreSQL,SQLite,Database,Python,RDB
Platform: UNKNOWN
Requires-Python: >=3.6
